{"query":{"normalized":[{"from":"Ronnie_Earl","to":"Ronnie Earl"}],"pages":{"1549236":{"pageid":1549236,"ns":0,"title":"Ronnie Earl","revisions":[{"contentformat":"text/x-wiki","contentmodel":"wikitext","*":":''This article refers to the musician.  For the district attorney of Travis County, Texas, see [[Ronnie Earle]].''\n{{Infobox musical artist\n|name = Ronnie Earl \n|image = RonnieEarl1996.jpg\n|caption = Earl playing the 1996 Riverwalk Blues Festival\n|image_size = <!-- Only for images narrower than 220 pixels -->\n|background = solo_singer\n|birth_name = Ronald Horvath\n|birth_date = {{birth date and age|mf=yes|1953|3|10|mf=y}}\n|birth_place =[[Queens]], [[New York City|New York]], [[United States]]\n|death_date = \n|genre = [[Blues]], [[blues rock]], [[rhythm and blues]], [[jazz]], [[jam band]]\n|occupation = [[Musician]]\n|instrument = [[Guitar]]\n|years_active = 1979&ndash;present\n|associated_acts= [[Roomful of Blues]], Ronnie Earl & The Broadcasters\n|label = [[Black Top Records|Black Top]], [[Telarc]], [[Rounder Records|Rounder]], [[Stony Plain Records|Stony Plain]], [[Verve Records|Verve]], [[Sledgehammer Blues]]/AudioQuest Music\n|website = {{URL|http://www.ronnieearl.com/}}\n}}\n\n'''Ronnie Earl''' (born '''Ronald Horvath''', March 10, 1953, [[Queens]], [[New York City|New York]], [[United States]])<ref name=\"amg\">{{cite web|last=Huey |first=Steve |url={{Allmusic|class=artist |id=p337/biography |pure_url=yes}} |title=Ronnie Earl |publisher=AllMusic |date=1953-03-10 |accessdate=2012-03-07}}</ref> is an [[United States|American]] [[blues]] [[guitarist]] and music instructor.\n\n==Career==\nEarl collected blues, [[jazz]], [[Rock music|rock]] and [[Soul music|soul]] [[gramophone record|records]] while growing up. He studied American History at [[C.W. Post College]] on Long Island for a year and a half, then moved to Boston to pursue a [[Bachelor's Degree]] in Special Education and Education at [[Boston University]] where he would graduate in 1975.<ref>{{cite web|url=http://www.ronnieearl.com/bio.html |title=Ronnie Earl's official website |publisher=Ronnieearl.com |date= |accessdate=2012-03-07}}</ref>  He spent a short time teaching handicapped children.  It was during his college years that he attended a [[Muddy Waters]] concert at the Jazz Workshop in Boston. After seeing Waters perform, Earl took a serious interest in the guitar, which he had first picked up in 1973. His first job was as a [[rhythm guitar]]ist at The Speakeasy,<ref>{{cite web|url=http://www.bluesaudience.com/speakeasy.html |title=The Blues Audience Speakeasy article |publisher=Bluesaudience.com |date=2004-03-07 |accessdate=2012-03-07}}</ref> a blues club in [[Cambridge, Massachusetts]]. In addition to playing in the Boston blues scene, Earl traveled twice by [[Greyhound Lines|Greyhound Bus]] to Chicago, where he was introduced to the Chicago blues scene by [[Koko Taylor]].\n\nLater he traveled to [[New Orleans]] and [[Austin, Texas]], where he spent time with [[Kim Wilson]], [[Jimmie Vaughan]] and The [[Fabulous Thunderbirds]]. In 1979 he joined [[Roomful of Blues]] as [[lead guitar]]ist for the [[band (music)|band]].\n\nHe began performing [[solo (music)|solo]] in 1986, in addition to playing with Roomful of Blues, and he released his first solo [[album]] on the [[Black Top Records]] [[record label|label]] with a quartet that focused on blues [[instrumental]]s. After leaving Roomful of Blues, he began collaborations with contemporaries Ron Levy and [[Jerry Portnoy]], [[Earl King]], [[Jimmy Rogers]], and [[Jimmy Witherspoon]].\n\nIn 1988, Earl formed his own band that he called The Broadcasters, named after the first Fender guitar which originally had been labeled The Broadcaster and was distributed in 1950. The first group of Broadcasters included [[Darrell Nulisch]]  (vocalist), [[Jerry Portnoy]] (harmonica), Steve Gomes (bass), and Per Hanson (drums). In 1988 they released their first album, ''Soul Searchin'', followed by ''Peace of Mind'' in 1990.  Their album ''Language of the Soul'' was released in 1994.  The lineup for the Broadcasters for that album was Bruce Katz (keyboards), Per Hanson (drums) and \"Rocket\" Rod Carey (bass).  The next album ''The Colour of Love'', featured Marc Quinones (percusion) and [[Gregg Allman]] (keyboards).  The association lead to Ronnie Earl and the Broadcasters opening for the [[Allman Brothers Band]] at Great Woods, and Warren Haynes (guitar for the Allman Brothers Band) sitting in with Ronnie Earl and the Broadcasters at Johnnie D's in Somerville. Later Katz joining the Gregg Allman Band.\n\nIn 2000, Earl was diagnosed with several medical ailments,<ref>{{cite web|url=http://www.ronnieearl.com/brianhollandinterview.html |title=Ronnie Earl Interview by Brian D. Holland |publisher=Ronnieearl.com |date= |accessdate=2012-03-07}}</ref> and scaled back his touring, as well as re-evaluating his career plans. The current group of Broadcasters, Jimmy Mouradian (bass), Dave Limina (organ), and [[Lorne Entress]] (drums), began playing together prior to the 2003 release of ''I Feel Like Going On'' and, in 2009, released ''Living in the Light'', their fifth release from [[Stony Plain Records]].<ref name=autogenerated1>{{cite web|url=http://www.stonyplainrecords.com/ronnieearl |title=Canada's Roots, Rock, Country, Folk & Blues Label |publisher=Stony Plain Records |date= |accessdate=2012-03-07}}</ref> In 2008, Ronnie Earl and the Broadcasters celebrated twenty years as a band, and by August, 2010, Ronnie Earl and the Broadcasters released ''Spread the Love''. \n\nEarl is a three-time [[Blues Music Award]] winner as Guitar Player of the Year.<ref>{{cite web|url=http://blues.about.com/od/bluesawards/a/2014-Blues-Music-Awards.htm |title=2014 Blues Music Awards Nominees and Winners |publisher=Blues.about.com |date= |accessdate=2014-05-16}}</ref> For five years he was an [[Associate Professor]] of Guitar at [[Berklee College of Music]] and, in 1995, he released ''Ronnie Earl: Blues Guitar with Soul'', an instructional VHS tape that was then re-released in DVD format in 2005. Earl was also the blues instructor at the 'National Guitar Summer Workshop'.\n\nIn early 2004, Earl's \"Hey Jose\" won in the third [[The Independent Music Awards|Independent Music Awards]] for Best Blues/R&B Song.<ref>{{cite web|url=http://www.musiciansatlas.com/jukebox/index.html |title=Independent Music Awards - 3rd Annual Winners |publisher=Musiciansatlas.com |date= |accessdate=2012-03-07}}</ref>\n\n== Discography ==\n=== [[Roomful of Blues]] === \n1979-1988  \n\n=== Ronnie Earl  and  the Broadcasters ===\n\n==== Studio albums ====\n*1983 Smoking (Kim Wilson, voc.)\n*1984 They Call Me Mr. Earl (Kim Wilson, voc.)\n*1988 Soul Searching\n*1990 Peace of Mind\n*1990 I Like It When It Rains\n*1991 Surrounded by Love\n*1992 Test of Time\n*1993 Still River\n*1994 Language of the Soul\n*1996 Eye to Eye\n*1996 Greateful Heart: Blues and Ballads\n*1997 The Colour of Love\n*2000 Healing Time\n*2001 & Friends\n*2003 I Feel Like Goin\u2019 On\n*2004 Now My Soul\n*2005 The [[Duke Robillard|Duke]] Meets the Earl  \n*2009 Living in the Light\n*2010 Spread the Love\n\n==== Live albums ====\n*1993 Blues and Forgiveness \u2013 Live in Europe (''also'' Blues Guitar Virtuoso \u2013 Live in Europe)\n*1994 Jimmy Rogers with Ronnie Earl and the Broadcasters\n*2007 Hope Radio\n*2013 Just for Today\n\n====Compilations ====\n*1985 Deep Blues (Kim Wilson, voc.)\n*1992 Test of Time: A Retrospective\n*1997 Plays Big Blues\n*2006 Heart and Soul: The Best of Ronnie Earl\n\n====Guest appearances ====\n[http://www.ilanakatz.com I've Got Something To Tell You\" - Blues and Old-time Fiddle with Ilana Katz Katz and friends, 2014]\n\n== DVD ==\n*2001 Blues Guitar with Soul\n*2008 Hope Radio Sessions\n\n==See also==\n* [[List of blues musicians]]\n* [[San Francisco Blues Festival]]\n* [[Long Beach Blues Festival]]\n* [[Black Top Records catalog]]\n\n==References==\n{{Reflist}}\n\n== External links ==\n* [http://www.ronnieearl.com/home.html Official website]\n\n{{Authority control|VIAF=85311440}}\n{{Persondata <!-- Metadata: see [[Wikipedia:Persondata]]. -->\n| NAME              = Earl, Ronnie\n| ALTERNATIVE NAMES =\n| SHORT DESCRIPTION = [[United States|American]] [[blues]] [[guitarist]]\n| DATE OF BIRTH     = March 10, 1953\n| PLACE OF BIRTH    = [[Queens]], [[New York City|New York]], [[United States]]\n| DATE OF DEATH     =\n| PLACE OF DEATH    =\n}}\n\n{{DEFAULTSORT:Earl, Ronnie}}\n[[Category:1953 births]]\n[[Category:Living people]]\n[[Category:American blues musicians]]\n[[Category:People from Queens, New York]]\n[[Category:American blues guitarists]]\n[[Category:Boston University alumni]]\n[[Category:Black Top Records artists]]\n[[Category:Contemporary blues musicians]]\n[[Category:Independent Music Awards winners]]"}]}}}}