{"query":{"normalized":[{"from":"Steve_James","to":"Steve James"}],"pages":{"696290":{"pageid":696290,"ns":0,"title":"Steve James","revisions":[{"contentformat":"text/x-wiki","contentmodel":"wikitext","*":"\n'''Steve James''' may refer to:\n* [[Steve James (actor)]], American actor\n* [[Steve James (Christian musician)]], Welsh contemporary Christian musician\n* [[Steve James (cricketer)]], English cricketer and journalist\n* [[Steve James (footballer)]], English football player\n* [[Steve James (producer)]], American producer and director \n* [[Steve James (snooker player)]], English snooker player\n* [[Steve James (blues musician)]], American blues musician\n* Steve James, [[Radio Television Hong Kong]] Radio Presenter\n* Steve James, better known as [[Steve Armstrong]] (born 1965), American professional wrestler\n\n{{hndis|name = James, Steve}}"}]}}}}